{
  "docx": [
    {
      "file": "c:\\Users\\rkdwl\\Desktop\\ai_pricing_promotion_strategy.docx",
      "exists": true,
      "paragraphs": 95,
      "top": [
        "AI 건설면허 양도가 산정 시스템",
        "홈보 전략 심층 분석 보고서",
        "서울건설정보 · 행정사사무소 하랑",
        "seoulmna.co.kr",
        "2026년 3월",
        "CONFIDENTIAL",
        "Executive Summary",
        "서울건설정보가 개발한 AI 건설면허 양도가 산정 시스템은 전국 최초의 데이터 기반 면허 가치 산정 도구입니다. 1,454건의 실제 매물 데이터와 1,146건의 가격학습 결과를 바탕으로, 건설면허 양도양수 시장에서 가장 큰 불투명성인 '양도가격 정보 비대칭'을 해결합니다.",
        "본 보고서는 이 혁신적인 도구를 최소 비용으로 최대 효과를 낼 수 있는 홈보 채널과 실행 전략을 산업 특성과 B2B 리드 제너레이션 관점에서 심층 분석합니다.",
        "1. 시장 분석: 왜 이 도구가 홈보가 되는가",
        "1-1. 타겟 고객의 핵심 Pain Point",
        "건설면허 양도양수 시장에서 매도인과 매수인 모두가 공통적으로 경험하는 가장 큰 고통은 '적정 양도가격을 알 수 없다'는 것입니다. 부동산과 달리 건설면허는 공시가격이나 실거래가 같은 공개 지표가 없고, 시평액·실적·공제조합 잔액·자본금·기술자 여부 등 변수가 복합적으로 작용하기 때문입니다.",
        "이 계산기는 바로 이 문제를 해결합니다. 도구 자체가 곧 홈보입니다. 고객이 계산기를 사용하는 순간 서울건설정보의 전문성과 데이터력을 체험하고, 자연스럽게 상담으로 연결됩니다.",
        "1-2. 경쟁 환경 분석",
        "현재 건설면허 양도양수 시장의 경쟁업체(명문, 미래, 디에이치, 아이디, k114 등)를 분석하면, 대부분 정적인 매물 리스트 나열 방식을 유지하고 있습니다. AI 기반의 양도가 산정 도구를 제공하는 곳은 전무합니다.",
        "이것이 홈보 관점에서 가장 큰 무기입니다: \"전국 최초\"라는 타이틀은 언론 보도, 커뮤니티 바이럴, 블로그 SEO 모든 채널에서 강력한 훅을 발휘합니다.",
        "2. 채널별 홈보 전략 우선순위",
        "하단 표는 비용 대비 효과, 실행 난이도, 타겟 고객 도달률을 종합적으로 고려한 채널별 우선순위입니다.",
        "3. 1순위 채널: 네이버 블로그 SEO 전략",
        "3-1. 핵심 전략: 계산기를 리드 마그넷으로 활용",
        "B2B 마케팅에서 무료 계산기/도구는 가장 강력한 리드 마그넷으로 입증되었습니다. 고객이 직접 데이터를 입력하면서 제품의 관련성을 체험하고, 동시에 귀중한 리드 정보를 수집할 수 있는 양방향 소통 경험을 만들어냅니다.",
        "블로그 글의 구조를 다음과 같이 설계합니다:",
        "고객의 Pain Point 공감 → 계산기 체험 유도 → 결과 해석 전문 상담 CTA",
        "모든 블로그 글 하단에 계산기 배너 + 카카오톡/전화 CTA 배치",
        "기존 seoulmna notice 글(348~360, 345)에도 계산기 내부링크 일괄 추가"
      ]
    },
    {
      "file": "c:\\Users\\rkdwl\\Desktop\\AI_?????_MOAT??_????_????.docx",
      "exists": false
    },
    {
      "file": "c:\\Users\\rkdwl\\Desktop\\AI_?????_????_??????.docx",
      "exists": false
    },
    {
      "file": "c:\\Users\\rkdwl\\Desktop\\IP_????_AI????????_2026.docx",
      "exists": false
    },
    {
      "file": "c:\\Users\\rkdwl\\Desktop\\IP????_??????_??????.docx",
      "exists": false
    }
  ],
  "pdf": {
    "file": "c:\\Users\\rkdwl\\Desktop\\Deep Research Backing Conversation for session None.pdf",
    "pages": 10,
    "preview": [
      "<h1>전국 단위 AI 기반 건설면허 양도양수 가치평가 시스템 효율적 홍보·세일즈·제품화 전략 보고서</h1> <p>기준일:\n2026-03-01</p>\n<h2>Executive summary</h2> <p> 본 제품은 “건설면허 양도양수·분할합병”이라는 고관여·고단가 이벤트에서,\n<strong>가격 확정이 아니라 ‘설명 가능한 거래 범위(근거+오차범위)’를 빠르게 제시</strong>하는 점이 강점이다. 현\n재 계산기 화면은 “유사도 기반 정밀 계산”, “예상 오차 범위·신뢰도·근거 매물 수”, “결과 전달(오픈채팅/이메일)”, “상\n담 요청 요약 자동 생성”, “참고용(법정/계약 효력 없음) 고지”를 포함해 신뢰 설계의 핵심 요소를 이미 갖춘 상태다.\n </p> <p> 시장 측면에서 건설업 기업체수는 2024년 기준 89,101개(종합 15,861개, 전문직별 공사업 73,240개)\n로 발표되어 잠재 모수가 크다. 다만 양도양수는 상시가 아니라 이벤트 기반이므로, <strong>대량 노출보다 고의도 수\n요(검색)  선점과  “진성  리드”  선별</strong>이  ROI를  좌우한다.   </p>  <p>  전략의  중심은  3축이다.  첫째,\n<strong>고의도 SEM(네이버/다음/구글) + 리타게팅</strong>으로 “산정 완료 → 자격심사 → 상담” 퍼널을 만든다\n(네이버 사이트검색광고는 클릭 시 과금되는 CPC 방식이며, 파워링크 순위는 연관성·입찰가·소재 품질 등을 종합해 결\n정된다고 안내).  둘째, <strong>신뢰형 SEO/콘텐츠</strong>로 “공고 30일” 등 일정 압박 니즈를 점유한다(전문\n건설협회 공고 안내는 30일 이상 공고를 명시).  셋째, <strong>파트너 유통(브로커/협회/전문가) + 화이트라벨</\nstrong>로 경쟁사가 따라오기 어려운 유통 모트를 만든다(전시회/협회 교육·세미나는 “검증 채널”로 신뢰와 제휴를 동\n시에 확보). 코리아빌드위크 2025 킨텍스는 참가기업 704개사, 2,514부스, 참관객 56,870명으로 공시되어 오프라인\n파트너링에 유리하다.  </p> <p> 핵심 운영 원칙은 “1인 운영자 과부하 방지”다. 상담 슬롯을 캡(예: 하루 4슬롯)으\n로 제한하고, 산정 완료 후 <strong>리드 스코어링·문서 준비도 기반으로 상담 우선순위를 자동 분류</strong>해야 한\n다. 카카오 채널은 1:1 채팅 메뉴 접근에 관리자 추가인증을 요구할 수 있어(개인정보 보호 목적) 운영 보안에도 도움이\n된다.  </p> <p> 규제·신뢰 측면에서, 광고성 메시지 발송은 정보통신망법 제50조에 따라 원칙적으로 명시적 사전\n동의가 필요하므로(예외 조항 존재), 리드 육성 시퀀스는 동의 기반으로만 설계해야 한다.  개인정보 처리는 개인정\n보보호위원회의 “개인정보 처리 통합 안내서(2025.7)” 및 “개인정보 처리방침 작성지침(2025.4)” 준거로 최소 수집·보\n유기간 명확화·위탁/제3자 제공 고지를 기본값으로 설정한다.  또한 2026.1.22 시행 “인공지능 발전과 신뢰 기반\n조성 등에 관한 기본법”은 ‘신뢰 기반 조성’을 목적에 포함하므로, 대외 커뮤니케이션을 “신뢰·책임·설명가능성” 중심으\n로 정렬하는 것이 전략적으로 유리하다.  </p>\n<h2>시장·타깃·포지셔닝</h2>\n<h3>수요 트리거와 고객 여정</h3> <p> 양도양수 관련 실무는 “공고(30일 이상)” 같은 고정 일정이 존재해, 고객이\n결정을 미루면 거래 리드타임이 늘어난다는 압박이 발생한다. 이 특성은 마케팅에서 “즉시 산정 → 근거 확인 → 상담\n연결”이라는 직접 전환형 여정을 만들기 좋다.  </p> <p> 현재 계산기는 입력값이 많을수록 오차범위가 줄어든다\n고 안내하며(면허/업종, 최근 실적, 시평, 공제조합 잔액 등), 결과에서 오차 범위·신뢰도·근거 매물 수를 제공하고, 결과\n전달(오픈채팅/이메일)과 상담 요청(요약 자동 생성)을 바로 수행할 수 있다.  </p>\n<h3>제품 터치포인트 구조</h3> <p> 운영 터치포인트는 “메인 도메인(배너/팝업/계산기 열기) → 계산기(산정/요약/\n상담) → 후속 상담”으로 설계되어 있으며, 실제로 seoulmna.co.kr 측 페이지는 “계산기 열기/새창 보기/카카오 상담”\n등 버튼형 동선을 구성한다.  </p>\n<h3>타깃 세그먼트 및 메시지 매트릭스</h3> <table border=\"1\" cellpadding=\"6\" cellspacing=\"0\"> <thead>\n<tr> <th>세그먼트</th> <th>주요 트리거</th> <th>핵심 니즈</th> <th>불신/반박</th> <th>핵심 메시지(권장)</\nth> <th>우선 채널</th> <th>CTA(과부하 방지형)</th> </tr> </thead> <tbody> <tr> <td>매도자(면허/법인)</\ntd> <td>정리·폐업·자금 회수, 일정 촉박</td> <td>“얼마 범위 + 언제 가능”</td> <td>AI 신뢰, 근거 부족</td>\n<td>“유사도 기반 산정 + 오차범위/근거매물수로 설명 가능한 범위를 먼저 확인” </td> <td>네이버/다음 검색 +\n리타게팅</td> <td>고득점만 ‘예약’, 그 외 ‘요약 제출’</td> </tr> <tr> <td>브로커/중개</td> <td>고객이 근거 요\n구, 빠른 제안 필요</td> <td>근거 자료, 리포트, 속도</td> <td>“어떤 데이터로?”</td> <td>“신뢰도·근거 매물 수를\n함께 제시해 고객 반박을 줄임” </td> <td>파트너 프로그램 + 업계 커뮤니티</td> <td>‘브로커용 리포트 템플릿’\n요청 폼</td> </tr> <tr> <td>양수 건설사</td> <td>업종 확장/입찰 준비</td> <td>리스크(등록기준/실태조사) 최\n1\n2\n3\n4\n5\n6\n7\n8\n9\n10\n1\n11\n1\n1\n1",
      "소화</td> <td>양수 후 행정 리스크</td> <td>“산정+체크리스트로 등록기준/실태조사 리스크를 먼저 점검” (협회 교\n육도 ‘실태조사 대응’ 과정을 운영) </td> <td>검색 + 세미나/전시</td> <td>서류 준비자만 30분 슬롯</td> </\ntr> <tr> <td>회계/세무</td> <td>결산/진단/자본금·잉여금 이슈</td> <td>재무 논리 정합, 보고용 근거</td> <td>\n법적  효력/책임</td>  <td>“참고용  산정(효력  없음)  +  근거  지표로  내부  설명자료를  빠르게  구성”  </td>\n<td>LinkedIn ABM + 검색</td> <td>‘케이스 미팅(비동기 요약 제출)’</td> </tr> <tr> <td>법무/행정</td> <td>절\n차·공고·서류 설계</td> <td>타임라인 정확, 분쟁 예방</td> <td>과장 광고/기만 우려</td> <td>“공고 30일 등 고정\n일정 역산 + 면책 고지로 분쟁 리스크 관리” </td> <td>세미나 + 검색</td> <td>‘일정표/서류 리스트 요청’</td>\n</tr> </tbody> </table>\n<h2>채널 전략</h2>\n<h3>채널별 전략 표</h3> <p> 아래 표는 채널별 “월 비용 범위(집행 예산/제작/운영 포함)”, “도달(리치) 산정 로직”,\n“장단점”, “권장 크리에이티브”를 제시한다. CPC/CPM 단가는 업종 경쟁도에 따라 편차가 크므로, 로직은 공식 과금 구\n조(플랫폼 문서) + 가정값 시뮬레이션 형태로 제시한다. </p>\n<table border=\"1\" cellpadding=\"6\" cellspacing=\"0\"> <thead> <tr> <th>채널</th> <th>퍼널 역할</th> <th>\n월 비용 범위(권장)</th> <th>도달/리드 산정 로직(예시)</th> <th>장점</th> <th>단점/주의</th> <th>추천 메시\n지/크리에이티브</th> </tr> </thead> <tbody> <tr> <td>SEO (네이버/구글)</td> <td>인지→관심→Trial</td>\n<td>150만~800만원</td> <td>콘텐츠×내부링킹×색인(robots/sitemap) → 노출 증가(수주~수개월)</td> <td>\n장기 CAC 하락, 신뢰 자산</td> <td>성과 지연, 기술 SEO 필요</td> <td>“공고 30일 역산”, “실태조사 대응”, “가격\n영향  항목(공제·실적·시평·잉여금)”</td>  </tr>  <tr>  <td>네이버  검색광고(사이트검색/파워링크)</td>  <td>관심\n→Trial→상담</td> <td>200만~1,500만원</td> <td><em>(CPC)</em> 클릭수≈예산/CPC, 리드≈클릭×산정완\n료율×유효상담율 (클릭 시 과금) </td> <td>고의도 유입, 즉시 성과</td> <td>CPC 상승 가능, 소재·랜딩 품질 필\n요</td> <td>헤드라인에 “오차범위·근거매물수” 포함 </td> </tr> <tr> <td>네이버 파워링크 순위 최적화</td>\n<td>효율 개선</td> <td>운영 내 포함</td> <td>연관성+입찰가+소재 품질 등 종합으로 순위 결정(공식) </td>\n<td>같은 예산으로 더 많은 고의도 클릭</td> <td>학습 필요(초기 변동)</td> <td>키워드-소재-랜딩의 1:1 정합성,\n“근거 제시” 강화</td> </tr> <tr> <td>네이버 브랜드검색</td> <td>인지(브랜드 방어)</td> <td>60만~1,140만원\n(정액, VAT 미포함 시작) </td> <td>브랜드 키워드 검색량 기반 정액 노출 </td> <td>경쟁사 침투 방지, 신뢰\n강화</td> <td>브랜드 검색수 전제</td> <td>“참고용(효력 없음)”+“근거/신뢰도” 한 화면 요약  </td> </tr>\n<tr>  <td>네이버  성과형  디스플레이(GFA)</td>  <td>인지→리타게팅→Trial</td>  <td>150만~1,000만원</td>\n<td><em>(CPM/CPC/CPV)</em> 과금 타입 선택 가능(공식)  </td> <td>리타게팅 효율, 유사타겟 확장</td>\n<td>초기 학습/소재 품질 의존</td> <td>배너: “근거매물수/신뢰도 확인 → 상담요약 자동 생성”  </td> </tr>\n<tr>  <td>다음(카카오)  키워드광고</td>  <td>관심→Trial</td>  <td>200만~1,200만원</td>  <td><em>(CPC)</\nem> 프리미엄링크는 클릭 시 과금, 실시간 입찰+품질지수 반영(공식) </td> <td>다음 검색 수요 추가 수확</td>\n<td>최상단 고정 어려움(품질지수 반영) </td> <td>“공고 30일, 지금 산정→상담” 타임프레셔</td> </tr> <tr>\n<td>카카오모먼트(비즈보드/디스플레이)</td> <td>인지→상담→전환</td> <td>200만~1,500만원</td> <td>픽셀/\nSDK 기반 전환 최적화 가능(공식) </td> <td>카카오톡 인벤토리로 상담 전환 빠름</td> <td>전환 이벤트 모수 필\n요</td> <td>비즈보드 유형(오브젝트/썸네일/마스킹/텍스트) 가이드 준수 </td> </tr> <tr> <td>카카오톡 채널/\n오픈채팅</td> <td>상담→전환</td> <td>0~50만원(운영 도구 수준)</td> <td>상담 유입→스크리닝→예약/비동기\n처리. 1:1 채팅은 관리자 추가인증 가능 </td> <td>마찰 낮은 상담, 모바일 최적</td> <td>운영 과부하 위험, 알\n림/응대 규정 필요</td> <td>초기 질문 5개 자동화(역할/시점/서류/지역/희망범위)</td> </tr> <tr> <td>GDN(구글\n디스플레이)</td> <td>인지→리타게팅</td> <td>150만~1,200만원</td> <td>디스플레이는 CPC 또는 CPM 입찰\n가능(공식) </td> <td>전국 확장, 리타게팅 저비용</td> <td>저의도 유입 가능 → 리타게팅 중심 권장</td> <td>\n산정완료자 리타게팅: “요약 제출하면 1:1 검증”</td> </tr> <tr> <td>YouTube</td> <td>인지→관심→리마케팅</\ntd> <td>200만~2,000만원</td> <td><em>(CPV)</em> 인스트림은 30초 시청(또는 상호작용) 시 조회로 집계/과금\n(공식) </td> <td>신뢰·전문성 전달, 복잡한 서비스 설명</td> <td>제작비/운영 난이도</td> <td>15초 데모: 입\n력→오차범위/근거매물수→상담요약 자동 생성 </td> </tr> <tr> <td>LinkedIn</td> <td>관심→상담(전문가·\n임원)</td> <td>150만~1,000만원</td> <td>입찰/전략 옵션을 고객센터에서 안내 </td> <td>회계/법무 리드 품\n질</td> <td>단가 높을 수 있음</td> <td>리드마그넷: “양도양수 일정표/실사 체크리스트(샘플)”</td> </tr> <tr>\n<td>업계 커뮤니티(카페/포럼)</td> <td>인지→신뢰→Trial</td> <td>0~300만원</td> <td>Q&A/사례 콘텐츠로\n12\n1\n10\n13\n1\n14\n15 15\n1\n16\n1\n17\n18\n19\n20\n6\n21\n22\n1\n23\n2",
      "유입→산정기 링크</td> <td>신뢰 기반 확산</td> <td>노골적 광고는 반감</td> <td>“공고 30일·절차·실태조사” 해\n설형 답변 </td> </tr> <tr> <td>협회/교육/세미나</td> <td>신뢰→상담</td> <td>1회 100만~500만원(후원/\n장소)</td> <td>교육 참석 실무자 대상 리드</td> <td>고품질 리드, 파트너링</td> <td>접근/섭외 필요</td> <td>\n협회가 ‘실태조사 대응’ 교육을 운영(니즈 검증) </td> </tr> <tr> <td>전시회(코리아빌드위크 등)</td> <td>인지\n→신뢰→파트너</td> <td>1회 800만~3,000만원</td> <td>2025 킨텍스: 참관객 56,870명(공시). 참가비: 독립 330\n만/조립 380만(VAT 별도/1부스)  </td> <td>검증 채널, 전국 파트너 발굴</td> <td>운영 인력/준비 부담</td>\n<td>3분 시연+QR 상담예약, ‘브로커/회계/법무’ 시간대별 미팅</td> </tr> <tr> <td>파트너 브로커</td> <td>전환\n(딜)</td> <td>성과수수료/리퍼럴</td> <td>파트너가 자체 고객 풀에 배포→산정기→리드 공유</td> <td>전환율\n↑, 확장 빠름</td> <td>브랜드/품질 통제 어려움</td> <td>화이트라벨+리포트 템플릿+면책 문구 패키지</td> </\ntr> </tbody> </table>\n<h3>SEO 실행 핵심</h3> <p> 네이버 SEO는 robots.txt, 사이트맵 제출, 검색로봇 접근 허용 등 기본기가 필수다\n(robots.txt는 루트 디렉터리에 위치해야 하며, 네이버 검색로봇이 규칙을 준수한다고 안내).  또한 네이버는 사이\n트맵 제출 시 도메인 일치, 용량(10MB), URL 수(50,000) 등 검증 기준을 제시한다.  </p> <p> 콘텐츠 전략은 네이\n버 블로그 검색 로직(C-Rank: 출처 신뢰도, D.I.A: 문서/경험 중심)의 방향에 맞춰 “실무 경험+체크리스트+사례” 누적\n을 중심으로 설계한다.  구글의 경우도 기본 SEO 가이드는 “검색 반영까지 시간이 걸릴 수 있음”을 전제로 하므로,\n90일 단위로 성과를 판단하는 편이 현실적이다.  </p>\n<h2>퍼널 운영·진성 리드·측정</h2>\n<h3>퍼널 기반 캠페인 구조</h3> <p> 퍼널은 <strong>Awareness → Interest → Trial(산정) → Consultation →\nConversion</strong>로 설계하되, 본 제품은 Trial에서 가치가 크게 발생하므로 <strong>“산정 완료율”과 “유효상\n담 전환율”</strong>을 최상위 KPI로 둔다. 계산기는 결과 화면에 오차범위·신뢰도·근거 매물 수를 제공하고, 결과 전\n달과 상담 요청(요약 자동 생성)을 포함한다.  </p>\n<h3>1인 운영자 기준 ‘진성 리드’ 선별 규칙</h3> <p> 상담 과부하를 막기 위해 “상담 슬롯 캡(예: 하루 4슬롯)”을 고\n정하고, 아래 기준으로 리드 스코어링(100점)을 적용한다. (점수는 내부 정책이며, 운영 데이터를 통해 2주 단위로 조정\n권장) </p> <table border=\"1\" cellpadding=\"6\" cellspacing=\"0\"> <thead> <tr> <th>항목</th> <th>가중치 예\n시</th>  <th>판정  기준  예시</th>  <th>자동  처리</th>  </tr>  </thead>  <tbody>  <tr>  <td>거래  시점</td>\n<td>25</td> <td>60일 이내(25) / 90일(15) / 180일+(5)</td> <td>90일+는 비동기 트랙</td> </tr> <tr> <td>역\n할</td> <td>15</td> <td>대표/임원(15) / 실무(10) / 정보 탐색(5)</td> <td>정보 탐색은 콘텐츠 라우팅</td> </\ntr> <tr> <td>입력 완성도</td> <td>20</td> <td>공제조합 잔액·실적·시평 등 핵심값 입력(상향) — 입력값이 많을수\n록 오차범위가 줄어든다고 안내 </td> <td>미완성은 “입력 가이드” 자동 발송</td> </tr> <tr> <td>서류 준비도\n</td> <td>25</td> <td>등기/재무/실적/행정처분 확인 등 제출 가능 (양도양수 절차 페이지에 제출서류 예시 존재)\n</td> <td>미준비는 “서류 체크리스트” 발송</td> </tr> <tr> <td>리스크 신호</td> <td>15</td> <td>행정처\n분 이력/부채·유동비율 등 위험 표식 시 ‘추가 실사 트랙’</td> <td>고위험은 예약 대신 “문서 선제출” 요구</td> </\ntr> </tbody> </table>\n<h3>리드 자격심사·트리아지 플로우차트</h3> <pre><code class=\"language-mermaid\">flowchart TD A[유입:\n검색/배너/전시회 QR/파트너] --> B{산정 완료?} B -- 아니오 --> B1[리타게팅: 공고 30일·절차 콘텐츠] --> A B -- 예 -->\nC[결과 화면: 오차범위·신뢰도·근거매물수 노출] C --> D[리드 스코어 계산] D --> E{스코어 ≥ 70} E -- 예 --> F[우선 트\n랙: 예약(하루 4슬롯) 또는 10분 콜] E -- 아니오 --> G{스코어 40~69} G -- 예 --> H[표준 트랙: 오픈채팅/이메일 비동기\n상담 + 요약 제출] G -- 아니오 --> I[교육 트랙: 체크리스트 자동 발송 + 7일 후 재평가] F --> J[상담] H --> J J --> K{서\n류 준비 완료?} K -- 예 --> L[실사/조건 정리 → 제안서/계약] K -- 아니오 --> M[보류: 서류 가이드 + 파트너(회계/법무)\n연결] L --> N[전환: 계약/수수료/파트너 딜]</code></pre>\n<h3>자동화·아웃소싱 옵션</h3> <p> 운영부하를 구조적으로 낮추려면 “초기 질문/분류/예약/CRM 기록”을 자동화하\n고,  고득점  리드만  사람이  응대하게  해야  한다.  </p>  <table  border=\"1\"  cellpadding=\"6\"  cellspacing=\"0\">\n<thead> <tr> <th>옵션</th> <th>무엇을 자동화/위임</th> <th>권장 적용 시점</th> <th>비고(근거)</th> </tr>\n</thead> <tbody> <tr> <td>카카오 챗봇</td> <td>5문항 스크리닝(역할/시점/서류/지역/희망 범위), 응답 기반 트\n24\n12\n25\n26\n27\n28\n29\n1\n1\n30\n3"
    ]
  }
}